dcaspt2_input_generator/__about__.py
dcaspt2_input_generator/__init__.py
dcaspt2_input_generator/__main__.py
dcaspt2_input_generator/dcaspt2_input_generator.py
dcaspt2_input_generator/components/color_settings.py
dcaspt2_input_generator/components/data.py
dcaspt2_input_generator/components/main_window.py
dcaspt2_input_generator/components/menu_bar.py
dcaspt2_input_generator/components/multi_process_settings.py
dcaspt2_input_generator/components/table_summary.py
dcaspt2_input_generator/components/table_widget.py
dcaspt2_input_generator/controller/color_settings_controller.py
dcaspt2_input_generator/controller/multi_process_controller.py
dcaspt2_input_generator/controller/save_default_settings_controller.py
dcaspt2_input_generator/controller/widget_controller.py
dcaspt2_input_generator/utils/args.py
dcaspt2_input_generator/utils/dir_info.py
dcaspt2_input_generator/utils/settings.py
dcaspt2_input_generator/utils/utils.py
dcaspt2_input_generator-0.8.0.dist-info/METADATA
dcaspt2_input_generator-0.8.0.dist-info/WHEEL
dcaspt2_input_generator-0.8.0.dist-info/entry_points.txt
dcaspt2_input_generator-0.8.0.dist-info/licenses/LICENSE
dcaspt2_input_generator-0.8.0.dist-info/RECORD
